{
  "file": "dangerous.py",
  "hash": "99d1bfe38c15d40c39af1f0d5f6229d337ad85479641895ccb3f6a324cc5607f",
  "size": 39,
  "extension": ".py",
  "module_type": "utility",
  "analysis_key": "78c59a71a631d57229590468c4c10c5b63e51f68",
  "static_candidates": [],
  "dynamic_candidates": [],
  "heuristic_signals": [],
  "exports": [],
  "conditional_flags": {
    "feature_flags": false,
    "env_checks": false,
    "conditional_loading": false
  },
  "structural_complexity": 0,
  "coupling_score": 0,
  "branching_score": 0,
  "risk_surface_score": 1,
  "complexity_total": 1,
  "function_count": 0,
  "class_count": 0,
  "branch_nodes": 0,
  "risk_flags": [
    "unsafe_eval_exec"
  ]
}
